Metadata-Version: 2.1
Name: bokoev
Version: 0.0.1
Summary: My Package
Author: Bokoev George
Author-email: goshik04@gmail.com
